inkster
