Metadata-Version: 2.1
Name: inkster
Version: 1.1.4
Summary: Inkster is possible for many things.
Home-page: https://github.com/OnyoCoder/inkster-py
Author: OnyoCoder
Author-email: InksterPY@protonmail.com
License: UNKNOWN
Project-URL: Discord, https://discord.gg/HUFtMsz
Keywords: splatter
Platform: UNKNOWN
Classifier: Programming Language :: Python :: 3
Classifier: License :: OSI Approved :: MIT License
Classifier: Operating System :: Microsoft :: Windows :: Windows 10
Requires-Python: >=3.8
